cflinkcpp.cpython-38-darwin.so
cflinkcpp-1.0a3.dist-info/LICENSE.md
cflinkcpp-1.0a3.dist-info/METADATA
cflinkcpp-1.0a3.dist-info/WHEEL
cflinkcpp-1.0a3.dist-info/top_level.txt
cflinkcpp-1.0a3.dist-info/RECORD
