Metadata-Version: 2.1
Name: cflinkcpp
Version: 1.0a3
Summary: C++ implementation of the Crazyflie link
Home-page: UNKNOWN
Author: UNKNOWN
Author-email: UNKNOWN
License: UNKNOWN
Platform: UNKNOWN
